dist_s1/__init__.py
dist_s1/__main__.py
dist_s1/aws.py
dist_s1/confirmation.py
dist_s1/constants.py
dist_s1/credentials.py
dist_s1/despeckling.py
dist_s1/dist_processing.py
dist_s1/localize_rtc_s1.py
dist_s1/packaging.py
dist_s1/py.typed
dist_s1/rio_tools.py
dist_s1/water_mask.py
dist_s1/workflows.py
dist_s1/data_models/__init__.py
dist_s1/data_models/algoconfig_model.py
dist_s1/data_models/data_utils.py
dist_s1/data_models/defaults.py
dist_s1/data_models/output_models.py
dist_s1/data_models/runconfig_model.py
dist_s1/etc/entrypoint.sh
dist_s1-2.0.9.dist-info/licenses/LICENSE
dist_s1-2.0.9.dist-info/METADATA
dist_s1-2.0.9.dist-info/WHEEL
dist_s1-2.0.9.dist-info/entry_points.txt
dist_s1-2.0.9.dist-info/top_level.txt
dist_s1-2.0.9.dist-info/RECORD
