Metadata-Version: 2.4
Name: dist-s1
Version: 2.0.9
Summary: The workflow to generate the DIST-S1 product
Author-email: "Richard West, Charlie Marshak, Talib Oliver-Cabrera, and Jungkyo Jung" <charlie.z.marshak@jpl.nasa.gov>
License: Apache-2.0
Project-URL: Homepage, https://github.com/opera-adt/dist-s1
Project-URL: Bug Tracker, https://github.com/opera-adt/dist-s1/issues
Project-URL: Discussions, https://github.com/opera-adt/dist-s1/discussions
Project-URL: Changelog, https://github.com/opera-adt/dist-s1/releases
Classifier: Intended Audience :: Developers
Classifier: Intended Audience :: Science/Research
Classifier: Programming Language :: Python :: 3
Classifier: Programming Language :: Python :: 3.12
Classifier: Programming Language :: Python :: 3.13
Classifier: Programming Language :: Python
Classifier: Topic :: Scientific/Engineering
Requires-Python: >=3.12
License-File: LICENSE
Requires-Dist: numpy
Requires-Dist: asf_search
Requires-Dist: geopandas
Requires-Dist: rasterio
Requires-Dist: distmetrics
Requires-Dist: dist-s1-enumerator
Requires-Dist: torch
Requires-Dist: geopandas
Requires-Dist: pandas
Requires-Dist: scipy
Requires-Dist: tile-mate
Requires-Dist: pydantic
Dynamic: license-file
